{
  "timestamp": "2026-05-06T08:25:04.811638",
  "data": {
    "indexes": [
      "上证指数: ¥11.49 🟢 -0.26%",
      "深证成指: ¥15107.55 🟢 -0.09%",
      "创业板指: ¥3677.15 🟢 -0.27%",
      "科创50: ¥51.48 🔴 +4.34%"
    ],
    "sample_stocks": [
      "中际旭创: 🔴 +1.48%",
      "新易盛: 🟢 -2.09%",
      "五洲新春: 🔴 +3.48%",
      "品渥食品: 🔴 +0.78%",
      "三安光电: 🟢 -1.94%",
      "紫光国微: 🔴 +1.90%",
      "宁德时代: 🟢 -2.02%",
      "比亚迪: 🟢 -2.30%",
      "中科创达: 🟢 -0.03%",
      "海康威视: 🔴 +4.25%"
    ],
    "total_stocks": 21,
    "valid_stocks": 21
  }
}